model_explorer_circle/circle_metadata.py
model_explorer_circle/circle_schema_generated.py
model_explorer_circle/main.py
model_explorer_circle-0.1.4.dist-info/LICENSE
model_explorer_circle-0.1.4.dist-info/METADATA
model_explorer_circle-0.1.4.dist-info/WHEEL
model_explorer_circle-0.1.4.dist-info/top_level.txt
model_explorer_circle-0.1.4.dist-info/RECORD
