Metadata-Version: 2.2
Name: model-explorer-circle
Version: 0.1.4
Summary: Model Explorer Circle Adaptor
Maintainer-email: NNFW <nnfw@samsung.com>
License: Apache Software License (Apache 2.0)
Project-URL: Repository, https://github.com/Samsung/ONE/tree/master/tools/model_explorer_circle/
Project-URL: Bug Reports, https://github.com/Samsung/ONE/issues
Keywords: circle,model-explorer,visualization
Classifier: Intended Audience :: Developers
Classifier: Programming Language :: Python :: 3.9
Classifier: Programming Language :: Python :: 3.10
Classifier: Programming Language :: Python :: 3.11
Classifier: Programming Language :: Python :: 3.12
Classifier: License :: OSI Approved :: Apache Software License
Classifier: Operating System :: OS Independent
Requires-Python: >=3.9
License-File: LICENSE
Requires-Dist: ai-edge-model-explorer
Requires-Dist: flatbuffers
